Workbook

Sheet Anafi
A2: ANALYSE FINANCIERE - UNIWAX
A4: Compte de résultat | G4: Compte de résultat en %
A5: (Clôture des comptes le 31 décembre de chaque exercice) | G5: =A5 -> (Clôture des comptes le 31 décembre de chaque exercice)
A7: En million de FCFA | B7: 2015 | C7: =1+B7 -> 2016 | D7: 2017 | E7: 2018 | G7: En % de la production | H7: =B7 -> 2015 | I7: =C7 -> 2016 | J7: =D7 -> 2017 | K7: =E7 -> 2018
A8: Chiffre d'affaires | B8: 39395 | C8: 37164 | D8: 37667 | E8: 38977 | G8: =A8 -> Chiffre d'affaires | H8: =B8/B$15 -> 0.98979925 | I8: =C8/C$15 -> 0.98213531 | J8: =D8/D$15 -> 1.0147633 | K8: =E8/E$15 -> 1.000154
A9: en millions de yards | B9: 25.621 | C9: =D9/1.002 -> 23.922156 | D9: 23.97 | E9: 25 | G9: =A9 -> en millions de yards | H9: =B9/B$8 -> 0.00065036172 | I9: =C9/C$8 -> 0.00064369163 | J9: =D9/D$8 -> 0.00063636605 | K9: =E9/E$8 -> 0.0006414039
A10: Croissance nominale | C10: =C8/B8-1 -> -0.056631552 | D10: =D8/C8-1 -> 0.013534603 | E10: =E8/D8-1 -> 0.034778453
A11: Croissance en volume | B11: =B9/24-1 -> 0.067541667 | C11: =C9/B9-1 -> -0.066306714 | D11: =D9/C9-1 -> 0.002 | E11: =E9/D9-1 -> 0.04297038 | G11: =A11 -> Croissance en volume | H11: =B11/B$8 -> 1.7144731e-06 | I11: =C11/C$8 -> -1.7841652e-06 | J11: =D11/D$8 -> 5.3096875e-08 | K11: =E11/E$8 -> 1.1024548e-06
A12: Croissance en prix | C12: =(1+C10)/(1+C11)-1 -> 0.010362248 | D12: =(1+D10)/(1+D11)-1 -> 0.01151158 | E12: =(1+E10)/(1+E11)-1 -> -0.007854419 | G12: =A12 -> Croissance en prix | H12: =B12/B$8 -> 0 | I12: =C12/C$8 -> 2.7882489e-07 | J12: =D12/D$8 -> 3.0561447e-07 | K12: =E12/E$8 -> -2.015142e-07
A13: + Production immobilisée | G13: =A13 -> + Production immobilisée | H13: =B13/B$15 -> 0 | I13: =C13/C$15 -> 0 | J13: =D13/D$15 -> 0 | K13: =E13/E$15 -> 0
A14: + Production stockée | B14: 406 | C14: 676 | D14: -548 | E14: -6 | G14: =A14 -> + Production stockée | H14: =B14/B$15 -> 0.010200749 | I14: =C14/C$15 -> 0.017864693 | J14: =D14/D$15 -> -0.014763329 | K14: =E14/E$15 -> -0.00015396064
A15: = Production | B15: =B8+B14+B13 -> 39801 | C15: =C8+C14+C13 -> 37840 | D15: =D8+D14+D13 -> 37119 | E15: =E8+E14+E13 -> 38971 | G15: =A15 -> = Production | H15: =B15/B$15 -> 1 | I15: =C15/C$15 -> 1 | J15: =D15/D$15 -> 1 | K15: =E15/E$15 -> 1
A16: - Achats consommés | B16: =SUM(B17:B19) -> 23406 | C16: =SUM(C17:C19) -> 21668 | D16: =SUM(D17:D19) -> 22215 | E16: =SUM(E17:E19) -> 23847 | G16: =A16 -> - Achats consommés | H16: =B16/B$15 -> 0.58807568 | I16: =C16/C$15 -> 0.57262156 | J16: =D16/D$15 -> 0.59848056 | K16: =E16/E$15 -> 0.61191655
A17: dont consommation matières premieres | B17: =18821-221 -> 18600 | C17: =17651-148 -> 17503 | D17: =18353+250 -> 18603 | E17: =20609+42 -> 20651 | G17: =A17 -> dont consommation matières premieres
A18: dont énergie | B18: 3161 | C18: =4115-126+176 -> 4165 | D18: =3988-582+206 -> 3612 | E18: =3508-484+172 -> 3196 | G18: =A18 -> dont énergie
A19: dont autres | B19: =4878-245+173-B18 -> 1645 | G19: =A19 -> dont autres
A20: = Marge brute | B20: =B15-B16 -> 16395 | C20: =C15-C16 -> 16172 | D20: =D15-D16 -> 14904 | E20: =E15-E16 -> 15124 | G20: =A20 -> = Marge brute | H20: =B20/B$15 -> 0.41192432 | I20: =C20/C$15 -> 0.42737844 | J20: =D20/D$15 -> 0.40151944 | K20: =E20/E$15 -> 0.38808345
A21: - Charges externes (communication et autres) | B21: 3110 | C21: 3088 | D21: 2952 | E21: 3233 | G21: =A21 -> - Charges externes (communication et autres) | H21: =B21/B$15 -> 0.07813874 | I21: =C21/C$15 -> 0.081606765 | J21: =D21/D$15 -> 0.079528005 | K21: =E21/E$15 -> 0.082959123
A22: = Valeur ajoutée | B22: =B20-B21 -> 13285 | C22: =C20-C21 -> 13084 | D22: =D20-D21 -> 11952 | E22: =E20-E21 -> 11891 | G22: =A22 -> = Valeur ajoutée | H22: =B22/B$15 -> 0.33378558 | I22: =C22/C$15 -> 0.34577167 | J22: =D22/D$15 -> 0.32199143 | K22: =E22/E$15 -> 0.30512432
A23: - Charges de personnel | B23: 4795 | C23: 5063 | D23: 5187 | E23: 5250 | G23: =A23 -> - Charges de personnel | H23: =B23/B$15 -> 0.12047436 | I23: =C23/C$15 -> 0.13380021 | J23: =D23/D$15 -> 0.13973976 | K23: =E23/E$15 -> 0.13471556
A24: - Impôts et taxes | B24: 583 | C24: 640 | D24: 592 | E24: 512 | G24: =A24 -> - Impôts et taxes | H24: =B24/B$15 -> 0.014647873 | I24: =C24/C$15 -> 0.016913319 | J24: =D24/D$15 -> 0.015948706 | K24: =E24/E$15 -> 0.013137974
A25: +/- Autres produits/ charges | B25: =681-250 -> 431 | C25: =1723-1617 -> 106 | D25: =1947-1515 -> 432 | E25: =378-63 -> 315 | G25: =A25 -> +/- Autres produits/ charges | H25: =B25/B$15 -> 0.010828874 | I25: =C25/C$15 -> 0.0028012685 | J25: =D25/D$15 -> 0.011638245 | K25: =E25/E$15 -> 0.0080829335
A26: = Excédent brut d'exploitation | B26: =B22-B23-B24+B25 -> 8338 | C26: =C22-C23-C24+C25 -> 7487 | D26: =D22-D23-D24+D25 -> 6605 | E26: =E22-E23-E24+E25 -> 6444 | G26: =A26 -> = Excédent brut d'exploitation | H26: =B26/B$15 -> 0.20949222 | I26: =C26/C$15 -> 0.19785941 | J26: =D26/D$15 -> 0.17794122 | K26: =E26/E$15 -> 0.16535372
A27: - Dotations aux amortissements | B27: 1068 | C27: 1061 | D27: 1168 | E27: =2261-1328 -> 933 | G27: =A27 -> - Dotations aux amortissements | H27: =B27/B$15 -> 0.026833497 | I27: =C27/C$15 -> 0.028039112 | J27: =D27/D$15 -> 0.031466365 | K27: =E27/E$15 -> 0.023940879
A28: = Résultat d'exploitation | B28: =B26-B27 -> 7270 | C28: =C26-C27 -> 6426 | D28: =D26-D27 -> 5437 | E28: =E26-E27 -> 5511 | G28: =A28 -> = Résultat d'exploitation | H28: =B28/B$15 -> 0.18265873 | I28: =C28/C$15 -> 0.1698203 | J28: =D28/D$15 -> 0.14647485 | K28: =E28/E$15 -> 0.14141285
A29: - Coût de l'endettement net | B29: =591-77 -> 514 | C29: =224 -> 224 | D29: 38 | E29: =99-67 -> 32 | G29: =A29 -> - Coût de l'endettement net | H29: =B29/B$15 -> 0.012914248 | I29: =C29/C$15 -> 0.0059196617 | J29: =D29/D$15 -> 0.0010237345 | K29: =E29/E$15 -> 0.0008211234
A30: + Autres éléments financiers | B30: =-157-570 -> -727 | C30: =45-190+3 -> -142 | D30: =162-115 -> 47 | G30: =A30 -> + Autres éléments financiers | H30: =B30/B$15 -> -0.018265873 | I30: =C30/C$15 -> -0.0037526427 | J30: =D30/D$15 -> 0.0012661979 | K30: =E30/E$15 -> 0
A31: + Eléments non récurrents | B31: 6 | C31: =6-15 -> -9 | D31: 6 | E31: 1 | G31: =A31 -> + Eléments non récurrents | H31: =B31/B$15 -> 0.00015074998 | I31: =C31/C$15 -> -0.00023784355 | J31: =D31/D$15 -> 0.00016164229 | K31: =E31/E$15 -> 2.5660106e-05
A32: = Résultat avant impôt | B32: =B28-B29+B30+B31 -> 6035 | C32: =C28-C29+C30+C31 -> 6051 | D32: =D28-D29+D30+D31 -> 5452 | E32: =E28-E29+E30+E31 -> 5480 | G32: =A32 -> = Résultat avant impôt | H32: =B32/B$15 -> 0.15162936 | I32: =C32/C$15 -> 0.15991015 | J32: =D32/D$15 -> 0.14687896 | K32: =E32/E$15 -> 0.14061738
A33: - Impôt sur les bénéfices | B33: 1678 | C33: 1967 | D33: 1435 | E33: 1283 | G33: =A33 -> - Impôt sur les bénéfices | H33: =B33/B$15 -> 0.042159745 | I33: =C33/C$15 -> 0.05198203 | J33: =D33/D$15 -> 0.038659447 | K33: =E33/E$15 -> 0.032921916
A34: Résultat net de l'ensemble consolidé | B34: =B32-B33 -> 4357 | C34: =C32-C33 -> 4084 | D34: =D32-D33 -> 4017 | E34: =E32-E33 -> 4197 | G34: =A34 -> Résultat net de l'ensemble consolidé | H34: =B34/B$15 -> 0.10946961 | I34: =C34/C$15 -> 0.10792812 | J34: =D34/D$15 -> 0.10821951 | K34: =E34/E$15 -> 0.10769547
A35: - Intérêts minoritaires | D35: 0 | E35: 0 | G35: =A35 -> - Intérêts minoritaires | H35: =B35/B$15 -> 0 | I35: =C35/C$15 -> 0 | J35: =D35/D$15 -> 0 | K35: =E35/E$15 -> 0
A36: = Résultat net part du groupe | B36: =B34-B35 -> 4357 | C36: =C34-C35 -> 4084 | D36: =D34-D35 -> 4017 | E36: =E34-E35 -> 4197 | G36: =A36 -> = Résultat net part du groupe | H36: =B36/B$15 -> 0.10946961 | I36: =C36/C$15 -> 0.10792812 | J36: =D36/D$15 -> 0.10821951 | K36: =E36/E$15 -> 0.10769547
A38: Tableau des flux de trésorerie
A40: =A7 -> En million de FCFA | B40: =B7 -> 2015 | C40: =C7 -> 2016 | D40: =D7 -> 2017 | E40: =E7 -> 2018
A41: Résultat net de l'ensemble consolidé | B41: =B34 -> 4357 | C41: =C34 -> 4084 | D41: =D34 -> 4017 | E41: =E34 -> 4197
A42: + Dotation aux amortissements | B42: =B27 -> 1068 | C42: =C27 -> 1061 | D42: =D27 -> 1168 | E42: =E27 -> 933
A43: + Charges et produits sans incidence sur la trésorerie | B43: 564 | C43: -81 | D43: -47 | E43: 725
A44: = Capacité d’autofinancement | B44: =B41+B42+B43 -> 5989 | C44: =C41+C42+C43 -> 5064 | D44: =D41+D42+D43 -> 5138 | E44: =E41+E42+E43 -> 5855
A45: - Variation du besoin en fonds de roulement d'exploitation | B45: -75 | C45: =C75-B75 -> 6556 | D45: =D75-C75 -> -1426 | E45: =E75-D75 -> -4077
A46: = Flux d’exploitation (1) | B46: =B44-B45 -> 6064 | C46: =C44-C45 -> -1492 | D46: =D44-D45 -> 6564 | E46: =E44-E45 -> 9932
A47: - Investissements industriels | B47: 989 | C47: 2133 | D47: 6005 | E47: =5744+46 -> 5790
A48: - Variation du besoin en fonds de roulement hors exploitation
A49: - Investissements financiers | B49: =250-13 -> 237 | C49: 61 | D49: =1-60 -> -59 | E49: -60
A50: + Produits nets des cessions | D50: 6 | E50: 1
A51: = Flux d'investissement (2) | B51: =-B47+B50-B49-B48 -> -1226 | C51: =-C47+C50-C49-C48 -> -2194 | D51: =-D47+D50-D49-D48 -> -5940 | E51: =-E47+E50-E49-E48 -> -5729
A52: Flux de trésorerie disponible après charges financières (1)+(2) | B52: =+B46+B51 -> 4838 | C52: =+C46+C51 -> -3686 | D52: =+D46+D51 -> 624 | E52: =+E46+E51 -> 4203
A53: + Augmentation (réduction) de capital | B53: 0 | C53: 10000 | D53: 0
A54: - Dividendes | B54: 2025 | C54: 2025 | D54: 4005 | E54: 4005
A55: = Réduction (augmentation) de l’endettement net | B55: =B52+B53-B54 -> 2813 | C55: =C52+C53-C54 -> 4289 | D55: =D52+D53-D54 -> -3381 | E55: =E52+E53-E54 -> 198
A56: Vérification | B56: -687 | C56: =C89-B89 -> -4289 | D56: =D89-C89 -> 3381 | E56: =E89-D89 -> -198
B57: =B56+B55 -> 2126 | C57: =C56+C55 -> 0 | D57: =D56+D55 -> 0 | E57: =E56+E55 -> 0
A59: Bilan
A60: =+A7 -> En million de FCFA | B60: =B7 -> 2015 | C60: =C40 -> 2016 | D60: =D40 -> 2017 | E60: =E40 -> 2018
A61: + Immobilisations incorporelles (brevet, licence, logiciel) | B61: 141 | C61: 88 | D61: 34 | E61: 43
A62: + Immobilisations incorporelles (fonds de commerce et autres) | B62: 100 | C62: 100 | D62: 100 | E62: 100
A63: + Immobilisations incorporelles (goodwill)
A64: + Immobilisations corporelles | B64: =25+1033+112+14+5273 -> 6457 | C64: =25+989+126+6290+80 -> 7510 | D64: =25+967+112+11114+182 -> 12400 | E64: 16563
A65: + Immobilisations financières | B65: 293 | C65: 232 | D65: 173 | E65: 113
A66: = Actifs immobilisés (1) | B66: =B61+B62+B63+B64+B65 -> 6991 | C66: =C61+C62+C63+C64+C65 -> 7930 | D66: =D61+D62+D63+D64+D65 -> 12707 | E66: =E61+E62+E63+E64+E65 -> 16819
A67: Stocks | B67: =SUM(B68:B70) -> 8578 | C67: =SUM(C68:C70) -> 9520 | D67: =SUM(D68:D70) -> 9485 | E67: 9938
A68: Dont matières premières | B68: 6053 | C68: 6387 | D68: 6730
A69: Dont en-cours | B69: 1063 | C69: 913 | D69: 794
A70: Dont intermédiaires et finis | B70: 1462 | C70: 2220 | D70: 1961
A71: + Clients | B71: =6412-57 -> 6355 | C71: =5058-295 -> 4763 | D71: =5912-359 -> 5553 | E71: =5260-647 -> 4613
A72: + Autres actifs d'exploitation | B72: 1351 | C72: 1832 | D72: 1997 | E72: =1724+132 -> 1856
A73: - Fournisseurs | B73: =6045-72 -> 5973 | C73: =-8+2859 -> 2851 | D73: =-30+5651 -> 5621 | E73: 9250
A74: - Autres dettes d'exploitation | B74: =2104+425+3586 -> 6115 | C74: =2155+341+16 -> 2512 | D74: =1728+348+12 -> 2088 | E74: =1891+17 -> 1908
A75: = Besoin en fonds de roulement (2) | B75: =+B67+B71-B73+B72-B74 -> 4196 | C75: =+C67+C71-C73+C72-C74 -> 10752 | D75: =+D67+D71-D73+D72-D74 -> 9326 | E75: =+E67+E71-E73+E72-E74 -> 5249
A76: Actifs hors exploitation | B76: 0 | C76: 0 | D76: 0
A77: - Passifs hors exploitation (fournisseurs d'immobilisations)
A78: = BFR hors exploitation (3) | B78: =B76-B77 -> 0 | C78: =C76-C77 -> 0 | D78: =D76-D77 -> 0 | E78: =E76-E77 -> 0
A79: Actif économique = (1)+(2)+(3) | B79: =B66+B75+B78 -> 11187 | C79: =C66+C75+C78 -> 18682 | D79: =D66+D75+D78 -> 22033 | E79: =E66+E75+E78 -> 22068
A80: Capitaux propres part du groupe | B80: 10416 | C80: 22200 | D80: 22170 | E80: 22403
A81: + Intérêts minoritaires
A82: - Impôts différés actifs
A83: + Impôts différés passifs
A84: + Subventions et CIR
A85: = Capitaux propres (4) | B85: =+B80+B81-B82+B83+B84 -> 10416 | C85: =+C80+C81-C82+C83+C84 -> 22200 | D85: =+D80+D81-D82+D83+D84 -> 22170 | E85: =+E80+E81-E82+E83+E84 -> 22403
A86: Dettes financières LT | B86: =29+575+1086 -> 1690 | C86: =2+575+1297 -> 1874 | D86: =575+1342 -> 1917 | E86: =575+653 -> 1228
A87: + Dettes financières CT | B87: 0 | C87: 178 | D87: 68
A88: - Trésorerie et équivalents de trésorerie | B88: =356+563 -> 919 | C88: =5070+238+262 -> 5570 | D88: =1064+472+586 -> 2122 | E88: =90+583+890 -> 1563
A89: = Endettement bancaire et financier net (5) | B89: =+B86+B87-B88 -> 771 | C89: =+C86+C87-C88 -> -3518 | D89: =+D86+D87-D88 -> -137 | E89: =+E86+E87-E88 -> -335
A90: Capitaux investis = (4)+(5) | B90: =B85+B89 -> 11187 | C90: =C85+C89 -> 18682 | D90: =D85+D89 -> 22033 | E90: =E85+E89 -> 22068
A91: Control | B91: =+B79-B90 -> 0 | C91: =+C79-C90 -> 0 | D91: =+D79-D90 -> 0 | E91: =+E79-E90 -> 0
A92: Vérification | B92: =IF((ABS(B79-B90)<0.1),"ok") -> ok | C92: =IF((ABS(C79-C90)<0.1),"ok") -> ok | D92: =IF((ABS(D79-D90)<0.1),"ok") -> ok | E92: =IF((ABS(E79-E90)<0.1),"ok") -> ok
B93: =B90-B79 -> 0 | C93: =C90-C79 -> 0 | D93: =D90-D79 -> 0

Sheet Questions et réponses
A1: CORRIGE QUIZ PREALABLE UNIWAX
B2: Questions/réponses | D2: Réponse | G2: Points | H2: Explication
A4: 1 | B4: Quel est le taux de croissance moyen annuel du chiffre d’affaires de Uniwax entre 2015 et 2018 ? Avec deux chiffres après la virgule. Si vous avez trouvé 15,483 %, tapez 15,48. | D4: =((Anafi!E8/Anafi!B8)^0.333-1)*100 -> -0.35458682 | G4: 2 | H4: (Chiffre d'affaires 2018/ chiffre d'affaires 2015) ^ 0,333-1
A6: =A4+1 -> 2 | B6: Quel est le taux de croissance moyen annuel en volume des ventes de Uniwax entre 2015 et 2018 ? Avec deux chiffres après la virgule. Si vous avez trouvé 15,483 %, tapez 15,48. | D6: =((Anafi!E9/Anafi!B9)^0.333-1)*100 -> -0.81373664 | G6: 2 | H6: (Ventes en volume 2018/ ventes en volume 2015) ^ 0,333-1
A8: =A6+1 -> 3 | B8: Pensez-vous que Uniwax ait fait des acquisitions significatives de nouvelles filiales entre 2015 et 2018 ? | G8: 1 | H8: Non, car sinon on verrait selon toute vraisemblance du goodwill ou du badwill parmi les immobilisations incorporelles du bilan. Il y aurait, par ailleurs, l'année de la première consolidation un bond du chiffre d'affaires du groupe qui intégrerait alors le chiffre d'affaires de la nouvelle filiale acquise.
B9: Oui
B10: Non | D10: X
A12: =A8+1 -> 4 | B12: Pensez-vous que Uniwax ait fait des cessions significatives de filiales entre 2015 et 2018 ? | G12: 1 | H12: Non, car sinon on verrait au compte de résultat une plus ou moins-value exceptionnelle.
B13: Oui
B14: Non | D14: X
A16: =A12+1 -> 5 | B16: Déduisez de vos réponses aux quatre questions précédentes, quel a été le taux de croissance moyen annuel en prix des ventes de Uniwax entre 2015 et 2018 ? Avec deux chiffres après la virgule. Si vous avez trouvé 15,483 %, tapez 15,48. | D16: =((D4/100-D6/100)/(1+D4/100))*100 -> 0.4607837 | G16: 1 | H16: 0
A18: =A16+1 -> 6 | B18: L’activité de Uniwax est-elle ? | G18: 2
B19: Saisonnière | H19: On ne voit pas très bien au nom de quoi elle serait saisonnière ou cyclique pour un bien de consommation courante d'assez faible valeur unitaire qui correspond à un besoin de la vie courante (s'habiller).
B20: Fortement cyclique
B21: Non saisonnière | D21: X
B22: Non cyclique | D22: X
A24: =A18+1 -> 7 | B24: Si vous deviez choisir entre ces 4 pourcentages pour la fraction des achats consommés correspondant à des coûts variables, lequel choisiriez-vous ? | G24: 2 | H24: Les achats consommés varient logiquement avec l'activité, peut-être pas à 100 % totalement, mais probablement beaucoup plus qu'à 50 %.
B25: 0
B26: 0.25
B27: 0.5
B28: 1 | D28: X
A30: =A24+1 -> 8 | B30: Si vous deviez choisir entre ces 4 pourcentages pour la fraction des charges externes correspondant à des coûts variables, lequel choisiriez-vous ? | G30: 2 | H30: Certaines charges externes sont des coûts fixes (comme la rémunération des auditeurs externes), d'autres sont des coûts variables comme les frais de publicité ou de logistique. Dès lors, 0 % et 100 % sont des réponses fausses. 10 % de coûts variables parait moins probable que 50 % puisque la charge externe donnée comme exemple sont les frais de communication qui sont variables.
B31: 0
B32: 0.1
B33: 0.5 | D33: X
B34: 1
A36: =A30+1 -> 9 | B36: Si vous deviez choisir entre ces 4 pourcentages pour la fraction des frais de personnel correspondant à des coûts variables, lequel choisiriez-vous ? | G36: 2 | H36: Quand l'activité d'une usine et de ses magasins baisse, certains postes peuvent être supprimés, les contrats d'intérimaires ne pas être renouvelés, mais surement pas pour 50 ou 100 % des effectifs !
B37: 0
B38: 0.1 | D38: X
B39: 0.5
B40: 1
A42: =A36+1 -> 10 | B42: Si vous deviez choisir entre ces 4 pourcentages pour la fraction des dotations aux amortissements correspondant à des coûts variables, lequel choisiriez-vous ? | G42: 2 | H42: Les dotations aux amortissements sont des coûts fixes qui ne varient que par plages d'activité
B43: 0 | D43: X
B44: 0.1
B45: 0.5
B46: 1
A47: =A42+1 -> 11 | B47: Calculez alors le point mort d'exploitation de Uniwax pour 2018, en reprenant les pourcentages estimés plus hauts et en considérant que le restant des coûts d'exploitation se partage à moitié entre coûts fixes et coûts variables. | D47: =(50%*Anafi!E21+90%*Anafi!E23+100%*Anafi!E27+50%*Anafi!E24-50%*Anafi!E25)/((Anafi!E8-100%*Anafi!E16-50%*Anafi!E21-10%*Anafi!E23-50%*Anafi!E24+50%*Anafi!E25)/Anafi!E8) -> 22294.602 | G47: 1 | H47: Point mort = Couts fixes / taux de marge sur coûts variables en % du CA = ( 50 % des charges externes + 90 % des frais de personnel + 100 % des dotations aux amortissements + 50 % des autres postes) / ( Ventes - 100 % des achats consommés - 50 % des charges externes - 10 % des frais de personnel - 50 % des autres postes)/ventes. Voir le calcul de la case D sur cette ligne.
A49: =A47+1 -> 12 | B49: Que pensez-vous de la position de Uniwax par rapport à son point mort ? | G49: 1 | H49: Être en 2018 à 38977/22295 - 1 = 75 % au dessus de son point mort est une situation très favorable, qui s'explique par l'importance de la marge opérationnelle à plus de 14 %, qui est le niveau des meilleurs groupes européens cotés en bourse d'une taille bien supérieure.
B51: Je suis assez inquiet car Uniwax se rapproche de son point mort.
B52: Uniwax est proche de son point mort, ce qui n'est pas une grande surprise car ses marges d'exploitation sont copieuses.
B53: Uniwax est très éloigné de son point mort, ce qui n'est pas une grande surprise car ses marges d'exploitation sont copieuses. | D53: X
A55: =A49+1 -> 13 | B55: Sans faire de calculs supplémentaires, pensez-vous qu'entre 2015 et 2018 Uniwax se soit : | G55: 2 | H55: Quand on se rapproche de son point mort, on amortit moins bien ses coûts fixes avec une marge sur coûts opérationnels qui baisse en montant absolu (en FCFA ici) ; des lors la marge d'exploitation baisse.
B56: Éloignée de son point mort car sa marge d'exploitation s'est accrue.
B57: Éloignée de son point mort car sa marge d'exploitation s'est réduite.
B58: Rapprochée de son point mort car sa marge d'exploitation s'est accrue.
B59: Rapprochée de son point mort car sa marge d'exploitation s'est réduite. | C59: X
A60: =A55+1 -> 14 | B60: Quand on regarde le taux d'impôt sur les sociétés apparent de Uniwax sur les 4 années, on se rend compte qu'il est : | G60: 2 | H60: En effet, le taux moyen apparent d'impôt sur les sociétés entre 2015 et 2018 ressort à 27,5 %, ce qui est un peu plus élevé que le taux ivoirien de 25 %.
B61: Proche du taux d'impôt sur les sociétés en Côte d'Ivoire (25 %) et que donc Uniwax est peu susceptible de faire de l'optimisation fiscale agressive. | D61: X
B62: Éloigné du taux d'impôt sur les sociétés en Côte d'Ivoire (25 %) et que donc Uniwax est peu susceptible de faire de l'optimisation fiscale agressive.
B63: Proche du taux d'impôt sur les sociétés en Côte d'Ivoire (25 %), et que donc Uniwax fait probablement de l'optimisation fiscale agressive.
B64: Éloigné du taux d'impôt sur les sociétés en Côte d'Ivoire (25 %), et que donc Uniwax fait probablement de l'optimisation fiscale agressive.
A66: =A60+1 -> 15 | B66: Calculez le ratio du BFR en jours de chiffre d’affaires (avec un taux de TVA de 18 %) pour 2015. Sans chiffre après la virgule : | D66: =Anafi!B75/Anafi!B8/1.18*365 -> 32.946193 | G66: 2 | H66: Besoin en fonds de roulement 2015 / Chiffre d'affaires 2015 / (1+ taux de TVA) *365. Voir le calcul de la case D sur cette ligne.
A68: =A66+1 -> 16 | B68: Calculez le ratio du BFR en jours de chiffre d’affaires (avec un taux de TVA de 18 %) pour 2016. Sans chiffre après la virgule : | D68: =Anafi!C75/Anafi!C8/1.18*365 -> 89.49065 | G68: 1 | H68: Besoin en fonds de roulement 2016 / Chiffre d'affaires 2016 / (1+ taux de TVA) *365. Voir le calcul de la case D sur cette ligne.
A70: =A68+1 -> 17 | B70: Calculez le ratio du BFR en jours de chiffre d’affaires (avec un taux de TVA de 18 %) pour 2017. Sans chiffre après la virgule : | D70: =Anafi!D75/Anafi!D8/1.18*365 -> 76.585268 | G70: 1 | H70: Besoin en fonds de roulement 2017 / Chiffre d'affaires 2017 / (1+ taux de TVA) *365. Voir le calcul de la case D sur cette ligne.
A72: =A70+1 -> 18 | B72: Calculez le ratio du BFR en jours de chiffre d’affaires (avec un taux de TVA de 18 %) pour 2018. Sans chiffre après la virgule : | D72: =Anafi!E75/Anafi!E8/1.18*365 -> 41.65614 | G72: 1 | H72: Besoin en fonds de roulement 2018 / Chiffre d'affaires 2018 / (1+ taux de TVA) *365. Voir le calcul de la case D sur cette ligne.
A74: =A72+1 -> 19 | B74: Calculez le délai de paiement moyen des clients au sens strict en jours de chiffre d'affaires pour 2016, sachant que le taux de TVA qui s’applique est de 18 %. Sans chiffre après la virgule : | D74: =Anafi!C71/Anafi!C8/1.18*365 -> 39.643226 | G74: 2 | H74: Clients 2016 / Chiffre d'affaires 2016 / (1+ taux de TVA) *365.Voir le calcul de la case D sur cette ligne.
A76: =A74+1 -> 20 | B76: Calculez le délai de paiement moyen des fournisseurs au sens strict pour 2015 en jours de coût des achats consommés et autres charges externes , sachant que le taux de TVA qui s’applique est de 18 %. Sans chiffre après la virgule : | D76: =Anafi!B73/(Anafi!B21+Anafi!B16)/1.18*365 -> 69.677949 | G76: 2 | H76: Fournisseurs / 1,18 / (Achats consommés + autres charges externes) * 365. Voir le calcul de la case D sur cette ligne.
A78: =A76+1 -> 21 | B78: Calculez le délai de paiement moyen des fournisseurs au sens strict pour 2016 en jours de coût des achats consommés et autres charges externes sachant que le taux de TVA qui s’applique est de 18 %. Sans chiffre après la virgule : | D78: =Anafi!C73/(Anafi!C16+Anafi!C21)/1.18*365 -> 35.622763 | G78: 1 | H78: Fournisseurs / 1,18 / (Achats consommés + autres charges externes) * 365. Voir le calcul de la case D sur cette ligne.
A80: =A78+1 -> 22 | B80: Calculez le délai de paiement moyen des fournisseurs au sens strict pour 2017 en jours de coût des achats consommés et autres charges externes sachant que le taux de TVA qui s’applique est de 18 %. Sans chiffre après la virgule : | D80: =Anafi!D73/(Anafi!D16+Anafi!D21)/1.18*365 -> 69.086468 | G80: 1 | H80: Fournisseurs / 1,18 / (Achats consommés + autres charges externes) * 365. Voir le calcul de la case D sur cette ligne.
A82: =A80+1 -> 23 | B82: Calculez le délai de paiement moyen des fournisseurs au sens strict pour 2018 en jours de coût des achats consommés et autres charges externes sachant que le taux de TVA qui s’applique est de 18 %. Sans chiffre après la virgule : | D82: =Anafi!E73/(Anafi!E16+Anafi!E21)/1.18*365 -> 105.65838 | G82: 1 | H82: Fournisseurs / 1,18 / (Achats consommés + autres charges externes) * 365. Voir le calcul de la case D sur cette ligne.
A84: =A82+1 -> 24 | B84: Calculez le délai de rotation des stocks de matière premières en jour d'achats consommés en 2015. | D84: =Anafi!B68/Anafi!B17*365 -> 118.78199 | G84: 2 | H84: Stocks de matières premières/ achats consommés*365. Voir le calcul de la case D sur cette ligne.
A86: =A84+1 -> 25 | B86: Calculez le délai de rotation des stocks de produits finis et intermédiaires en jour de chiffre d'affaires en 2017. | D86: =Anafi!D70/Anafi!D8*365 -> 19.002442 | G86: 2 | H86: Stocks de produits finis/ chiffre d'affaires*365. Voir le calcul de la case D sur cette ligne.
A88: =A86+1 -> 26 | B88: Calculez le ratio des immobilisations corporelles nettes sur les immobilisations corporelles brutes pour 2015. Sans chiffre après la virgule. Si vous avez trouvé 15,483 %, tapez 15. | D88: =Anafi!B64/'Annexe 2'!C12*100 -> 32.3335 | G88: 2 | H88: Immobilisations corporelles nettes/ immobilisations corporelles brutes. Voir le calcul de la case D sur cette ligne.
A90: =A88+1 -> 27 | B90: Calculez le ratio des immobilisations corporelles nettes sur les immobilisations corporelles brutes pour 2018 | D90: =Anafi!E64/'Annexe 2'!F12*100 -> 54.909826 | G90: 1 | H90: Immobilisations corporelles nettes/ immobilisations corporelles brutes. Voir le calcul de la case D sur cette ligne.
A92: =A90+1 -> 28 | B92: Calculez le ratio d’endettement bancaire et financier net par rapport à l’excédent brut d’exploitation d'Uniwax pour 2015. Avec un chiffre après la virgule : | D92: =Anafi!B89/Anafi!B26 -> 0.092468218 | G92: 2 | H92: Dettes bancaires et financières nettes 2015 / Excédent brut d'exploitation 2015. Voir le calcul de la case D sur cette ligne.
A94: =A92+1 -> 29 | B94: Calculez le ratio d’endettement bancaire et financier net par rapport à l’excédent brut d’exploitation d'Uniwax pour 2018. Avec un chiffre après la virgule : | D94: =Anafi!E89/Anafi!E26 -> -0.051986344 | G94: 1 | H94: Dettes bancaires et financières nettes 2018 / Excédent brut d'exploitation 2018. Voir le calcul de la case D sur cette ligne.
A96: =A94+1 -> 30 | B96: Ces ratios que vous venez de calculer aux deux questions précédentes sont-ils pertinents ? | G96: 2
B97: Oui, car Uniwax est à maturité. | H97: Certes, mais cela n'a rien à voir.
B98: Oui, car les variations du BFR sont négligeables en représentant de l'ordre de 3 % de l'EBE, entre 2015 à 2018. | D98: X | H98: Le cumul des EBE de 2015 à 2018 est de 29 Md FCFA et celui des variations du BFR de 1 Md FCFA, soit environ 3 % du solde précédent. La très grande majorité de l'EBE se transforme donc en flux de trésorerie sans être ponctionnée au passage par les variations du BFR, ce qui donne donc toute sa pertinence à ce ratio.
B99: Non, car les variations du BFR sont de l'ordre de 40 % de l'EBE de 2015 à 2018. | H99: Voir au-dessus.
B100: Non, car Uniwax est dans un métier où l'excédent brut d'exploitation est erratique. | H100: Factuellement faux lorsque l'on regarde l'historique des 4 dernières années.
A102: =A96+1 -> 31 | B102: Calculez la rentabilité économique pour 2016 en utilisant comme taux de l’impôt sur les sociétés un taux d'impôt de 25 %. Avec un chiffre après la virgule. Si vous avez trouvé 15 %, tapez 15. | D102: =Anafi!C28*(1-25%)/Anafi!C79*100 -> 25.797559 | G102: 2 | H102: Résultat d'exploitation x (1 - taux d'impôt sur les sociétés) / Montant comptable de l'actif économique. Voir le calcul de la case D sur cette ligne.
A104: =A102+1 -> 32 | B104: Calculez la rentabilité économique pour 2018 en utilisant comme taux de l’impôt sur les sociétés un taux d'impôt de 25 %. Avec un chiffre après la virgule. Si vous avez trouvé 15 %, tapez 15. | D104: =Anafi!E28*(1-25%)/Anafi!E79*100 -> 18.729608 | G104: 1 | H104: Résultat d'exploitation x (1 - taux d'impôt sur les sociétés) / Montant comptable de l'actif économique. Voir le calcul de la case D sur cette ligne.
A106: =A104+1 -> 33 | B106: Calculez le taux de rotation de l’actif économique pour 2015. Avec un chiffre après la virgule : | D106: =Anafi!B8/Anafi!B79 -> 3.5214982 | G106: 2 | H106: Chiffre d'affaires / actif économique. Voir le calcul de la case D sur cette ligne.
A108: =A106+1 -> 34 | B108: Calculez le taux de rotation de l’actif économique pour 2018. Avec un chiffre après la virgule : | D108: =Anafi!E8/Anafi!E79 -> 1.7662226 | G108: 1 | H108: Chiffre d'affaires / actif économique. Voir le calcul de la case D sur cette ligne.
A110: =A108+1 -> 35 | B110: Quel est le principal facteur expliquant l'évolution de la rentabilité économique après impôt entre 2015 et 2018 ? | G110: 2
B111: La baisse du taux de rotation de l'actif économique du fait de la réalisation des investissements non encore productifs. | D111: X | H111: Comme l'illustre la baisse du taux de rotation de l'actif économique vue à la question précédente, elle est due à la progression des immobilisations corporelles du fait de l'extension de l'usine qui n'est pas encore entrée en phase de production.
B112: La hausse de l'effet de levier. | H112: Par construction l'effet de levier n'a pas d'impact sur la rentabilité économique.
B113: La baisse de l'effet de levier. | H113: Par construction l'effet de levier n'a pas d'impact sur la rentabilité économique.
B114: La baisse du taux d'impôt apparent.
A116: =A110+1 -> 36 | B116: Calculez la rentabilité des capitaux propres de Uniwax pour 2016. Avec un chiffre après la virgule. Si vous avez trouvé 15 %, tapez 15 : | D116: =(Anafi!C36-Anafi!C31)/Anafi!C85*100 -> 18.436937 | G116: 2 | H116: (Résultat net - éléments non récurrents) / Capitaux propres. Voir le calcul de la case D sur la ligne.
A118: =A116+1 -> 37 | B118: Pourquoi la rentabilité des capitaux propres en 2016 est-elle inférieure à la rentabilité économique de 2016 ? | G118: 2 | H118: Sans commentaire supplémentaire.
B119: Parce que vous avez fait une erreur de calcul.
B120: Parce que Uniwax est très endettée.
B121: Parce que Uniwax a une dette négative et que l'effet de levier de la dette marche à l'envers | D121: X
B122: Parce que le coût de la dette de Uniwax est supérieur à son taux de rentabilité économique.
B124: Total | G124: =SUM(G4:G121) -> 59

Sheet Annexe 2
B10: En M de FCFA | C10: 2015 | D10: =C10+1 -> 2016 | E10: =D10+1 -> 2017 | F10: =E10+1 -> 2018
B12: Immobilisations corporelles brutes | C12: =3981+405+15226+358 -> 19970 | E12: 27368 | F12: 30164
